mcp_compose/__init__.py
mcp_compose/__main__.py
mcp_compose/__version__.py
mcp_compose/auth.py
mcp_compose/auth_jwt.py
mcp_compose/auth_middleware.py
mcp_compose/auth_oauth2.py
mcp_compose/authz.py
mcp_compose/cli.py
mcp_compose/composer.py
mcp_compose/config.py
mcp_compose/config_loader.py
mcp_compose/discovery.py
mcp_compose/exceptions.py
mcp_compose/metrics.py
mcp_compose/oauth_client.py
mcp_compose/otel.py
mcp_compose/process.py
mcp_compose/process_manager.py
mcp_compose/tool_authz.py
mcp_compose/tool_manager.py
mcp_compose/tool_proxy.py
mcp_compose/api/__init__.py
mcp_compose/api/app.py
mcp_compose/api/dependencies.py
mcp_compose/api/middleware.py
mcp_compose/api/models.py
mcp_compose/api/routes/__init__.py
mcp_compose/api/routes/auth.py
mcp_compose/api/routes/config.py
mcp_compose/api/routes/health.py
mcp_compose/api/routes/oauth.py
mcp_compose/api/routes/servers.py
mcp_compose/api/routes/settings.py
mcp_compose/api/routes/status.py
mcp_compose/api/routes/tools.py
mcp_compose/api/routes/translators.py
mcp_compose/api/routes/version.py
mcp_compose/providers/__init__.py
mcp_compose/providers/auth_anaconda.py
mcp_compose/proxy/__init__.py
mcp_compose/proxy/translator.py
mcp_compose/transport/__init__.py
mcp_compose/transport/base.py
mcp_compose/transport/http_stream.py
mcp_compose/transport/sse_server.py
mcp_compose/transport/stdio.py
mcp_compose/ui/dist/index.html
mcp_compose/ui/dist/assets/index-C-KrfweE.css
mcp_compose/ui/dist/assets/index-mfdxmUm-.js
mcp_compose-0.1.9.dist-info/METADATA
mcp_compose-0.1.9.dist-info/WHEEL
mcp_compose-0.1.9.dist-info/entry_points.txt
mcp_compose-0.1.9.dist-info/licenses/LICENSE
mcp_compose-0.1.9.dist-info/RECORD
