Metadata-Version: 2.4
Name: mcp_compose
Version: 0.1.9
Project-URL: Home, https://github.com/datalayer/mcp-compose
Project-URL: Documentation, https://github.com/datalayer/mcp-compose
Project-URL: Repository, https://github.com/datalayer/mcp-compose
Project-URL: Issues, https://github.com/datalayer/mcp-compose/issues
Author-email: Datalayer <info@datalayer.ai>
License: BSD 3-Clause License
License-File: LICENSE
Keywords: Composition,MCP,Model Context Protocol,Server
Classifier: Intended Audience :: Developers
Classifier: Intended Audience :: System Administrators
Classifier: License :: OSI Approved :: BSD License
Classifier: Programming Language :: Python
Classifier: Programming Language :: Python :: 3
Classifier: Programming Language :: Python :: 3.10
Classifier: Programming Language :: Python :: 3.11
Classifier: Programming Language :: Python :: 3.12
Requires-Python: >=3.10
Requires-Dist: cryptography>=41.0.0
Requires-Dist: fastapi>=0.104.0
Requires-Dist: httpx>=0.25.0
Requires-Dist: importlib-metadata>=4.8.0
Requires-Dist: mcp[cli]>=1.2.1
Requires-Dist: prometheus-client
Requires-Dist: psutil>=5.9.0
Requires-Dist: pydantic>=2.0.0
Requires-Dist: pyjwt>=2.8.0
Requires-Dist: python-dotenv>=1.0.0
Requires-Dist: sse-starlette
Requires-Dist: sse-starlette>=1.8.0
Requires-Dist: toml>=0.10.2
Requires-Dist: tomli>=2.0.0; python_version < '3.11'
Requires-Dist: typing-extensions>=4.0.0
Requires-Dist: uvicorn[standard]>=0.24.0
Provides-Extra: dev
Requires-Dist: pre-commit>=3.0.0; extra == 'dev'
Provides-Extra: lint
Requires-Dist: mypy>=1.0.0; extra == 'lint'
Requires-Dist: ruff>=0.1.0; extra == 'lint'
Provides-Extra: otel
Requires-Dist: opentelemetry-api>=1.20.0; extra == 'otel'
Requires-Dist: opentelemetry-exporter-otlp-proto-http>=1.20.0; extra == 'otel'
Requires-Dist: opentelemetry-sdk>=1.20.0; extra == 'otel'
Provides-Extra: test
Requires-Dist: pytest-asyncio>=0.21.0; extra == 'test'
Requires-Dist: pytest-cov>=4.0.0; extra == 'test'
Requires-Dist: pytest>=7.0; extra == 'test'
